{"container_type": "Author", "filled": ["basics", "publications", "indices", "counts"], "scholar_id": "4yD2aTkAAAAJ", "source": "AUTHOR_PROFILE_PAGE", "name": "Jinsong Li", "url_picture": "https://scholar.googleusercontent.com/citations?view_op=view_photo&user=4yD2aTkAAAAJ&citpid=6", "affiliation": "The Chinese University of Hong Kong", "interests": ["Large Model", "Multi-modal Learning"], "email_domain": "@pjlab.org.cn", "homepage": "https://li-jinsong.github.io/", "citedby": 171, "publications": {"4yD2aTkAAAAJ:qjMakFHDy7sC": {"container_type": "Publication", "source": "AUTHOR_PUBLICATION_ENTRY", "bib": {"title": "ShareGPT4V: Improving Large Multi-Modal Models with Better Captions", "pub_year": "2024"}, "filled": false, "author_pub_id": "4yD2aTkAAAAJ:qjMakFHDy7sC", "num_citations": 140, "citedby_url": "https://scholar.google.com/scholar?oi=bibs&hl=en&cites=7333634103049317300,15449078517261202135", "cites_id": ["7333634103049317300", "15449078517261202135"]}, "4yD2aTkAAAAJ:ufrVoPGSRksC": {"container_type": "Publication", "source": "AUTHOR_PUBLICATION_ENTRY", "bib": {"title": "Are We on the Right Way for Evaluating Large Vision-Language Models?", "pub_year": "2024"}, "filled": false, "author_pub_id": "4yD2aTkAAAAJ:ufrVoPGSRksC", "num_citations": 28, "citedby_url": "https://scholar.google.com/scholar?oi=bibs&hl=en&cites=4459148544604166048", "cites_id": ["4459148544604166048"]}, "4yD2aTkAAAAJ:LkGwnXOMwfcC": {"container_type": "Publication", "source": "AUTHOR_PUBLICATION_ENTRY", "bib": {"title": "ShareGPT4Video: Improving Video Understanding and Generation with Better Captions", "pub_year": "2024"}, "filled": false, "author_pub_id": "4yD2aTkAAAAJ:LkGwnXOMwfcC", "num_citations": 2, "citedby_url": "https://scholar.google.com/scholar?oi=bibs&hl=en&cites=5437535431763980848", "cites_id": ["5437535431763980848"]}, "4yD2aTkAAAAJ:WF5omc3nYNoC": {"container_type": "Publication", "source": "AUTHOR_PUBLICATION_ENTRY", "bib": {"title": "Half-Xor: A Fully-Dynamic Sketch for Estimating the Number of Distinct Values in Big Tables", "pub_year": "2024"}, "filled": false, "author_pub_id": "4yD2aTkAAAAJ:WF5omc3nYNoC", "num_citations": 1, "citedby_url": "https://scholar.google.com/scholar?oi=bibs&hl=en&cites=583081110684035330", "cites_id": ["583081110684035330"]}}, "citedby5y": 171, "hindex": 2, "hindex5y": 2, "i10index": 2, "i10index5y": 2, "cites_per_year": {"2023": 1, "2024": 170}, "updated": "2024-07-02 08:15:00.060659"}